{
  "turn": 2,
  "question": {
    "alias": "q_rituals_since_then_2",
    "label": "Rituals since then",
    "name": "I've noticed you've been quieter in a few team rituals since the promotion decision — what's changed there?",
    "description": "Observation-first probe into the visible engagement shift without forcing a diagnosis.",
    "purpose": "wellbeing",
    "stage": "observation",
    "axis_effects": {
      "engagement": 3,
      "wellbeing": 1
    },
    "source": "generated"
  },
  "answer": "After the promotion decision, I was not clear on what really needed to change.",
  "skipped": false,
  "assessment": {
    "deltas": {},
    "note": "The answer names post-decision uncertainty about what needed to change, which is a strong clarity deficit."
  },
  "new_queue": [
    {
      "alias": "q_what_landed_3",
      "label": "What landed",
      "name": "What part of the feedback from that decision actually landed with you?"
    },
    {
      "alias": "q_unsaid_reaction",
      "label": "Unsaid reaction",
      "name": "What did you choose not to say after that decision?"
    },
    {
      "alias": "q_next_step_picture",
      "label": "Next-step picture",
      "name": "What concrete path forward feels real to you right now?"
    },
    {
      "alias": "q_mentoring_shape_8",
      "label": "Mentoring shape",
      "name": "What is the mentoring program taking space for in your week?"
    },
    {
      "alias": "q_core_path_tradeoff",
      "label": "Core path tradeoff",
      "name": "What are you choosing not to spend time on because of the mentoring program?"
    },
    {
      "alias": "q_support_needed_24",
      "label": "Support needed",
      "name": "What would help make the next couple of weeks steadier for you?"
    }
  ],
  "issues": [
    "dropped off-signature delta: clarity -3"
  ],
  "axis_state": {
    "wellbeing": {
      "score": -2,
      "history": [
        {
          "q": "q_intro_off_connection",
          "delta": -1,
          "answer_excerpt": "I have been less present in rituals, yes."
        }
      ]
    },
    "engagement": {
      "score": -2,
      "history": [
        {
          "q": "q_intro_off_connection",
          "delta": -1,
          "answer_excerpt": "I have been less present in rituals, yes."
        }
      ]
    },
    "clarity": {
      "score": 0,
      "history": []
    },
    "growth": {
      "score": 0,
      "history": []
    }
  }
}