{"assessment":{"deltas":[{"axis":"clarity","delta":-1},{"axis":"growth","delta":-3}],"note":"Fast-changing priorities are leaving him unsure what to optimize for, signaling mild role clarity loss and strong growth-disrupting uncertainty. [THREAD-DEFERRED] 'what to optimize for' is a concrete thread, but drill cap requires advancing stages."},"new_queue":[{"ref_alias":"q_intro_off_energy","label":"Energy read","name":"How's your energy been lately — separately from how work is going?","description":"Separates energy from output; avoids leading with 'is something wrong'.","purpose":"wellbeing","stage":"landing","axis_effects":[{"axis":"wellbeing","delta":3}]},{"ref_alias":"q_support_next_step","label":"Support next step","name":"What would help most from me right now?","description":"Opens the support stage by inviting him to name the most useful help.","purpose":"wellbeing","stage":"support","axis_effects":[{"axis":"clarity","delta":1},{"axis":"wellbeing","delta":1}]}]}