{
  "turn": 2,
  "question": {
    "alias": "q_decision_making_map_3",
    "label": "Decision-making map",
    "name": "When you say 'how decisions are really made here,' what feels most unclear?",
    "description": "Drills into the specific decision-making gap Riley just named so the manager can remove the right friction.",
    "purpose": "topic",
    "stage": "settling",
    "axis_effects": {
      "clarity": 1
    },
    "source": "planner_added"
  },
  "answer": "I can trace most request paths now, though I still miss historical context behind certain tradeoffs.",
  "skipped": false,
  "assessment": {
    "deltas": {
      "clarity": -1
    },
    "note": "He can follow request paths but still lacks historical context behind tradeoffs, which is a mild remaining clarity gap."
  },
  "new_queue": [
    {
      "alias": "q_tradeoff_context_2",
      "label": "Tradeoff context",
      "name": "Which tradeoffs feel hardest to read without the backstory?"
    },
    {
      "alias": "q_ownership_edges_3",
      "label": "Ownership edges",
      "name": "Where do the ownership boundaries still feel fuzzy to you?"
    },
    {
      "alias": "q_good_call_line",
      "label": "Good call line",
      "name": "What feels like a safe call for you to make on your own right now?"
    },
    {
      "alias": "q_missing_context",
      "label": "Missing context",
      "name": "What are you still waiting to understand before you change an architecture assumption?"
    },
    {
      "alias": "q_decision_risk",
      "label": "Decision risk",
      "name": "Where does the current design feel riskiest to you?"
    },
    {
      "alias": "q_support_network_2",
      "label": "Support network",
      "name": "Who would you want to pull in first when you need context fast?"
    },
    {
      "alias": "q_next_support_4",
      "label": "Next support",
      "name": "What would make the next couple of weeks steadier for you?"
    }
  ],
  "issues": [],
  "axis_state": {
    "wellbeing": {
      "score": 0,
      "history": [
        {
          "q": "q_landing_check_in_4",
          "delta": 1,
          "answer_excerpt": "I am comfortable reading the services, but I am less sure how decisions are really made here."
        }
      ]
    },
    "engagement": {
      "score": -1,
      "history": []
    },
    "clarity": {
      "score": -2,
      "history": [
        {
          "q": "q_landing_check_in_4",
          "delta": -1,
          "answer_excerpt": "I am comfortable reading the services, but I am less sure how decisions are really made here."
        },
        {
          "q": "q_decision_making_map_3",
          "delta": -1,
          "answer_excerpt": "I can trace most request paths now, though I still miss historical context behind certain tradeoffs."
        }
      ]
    },
    "growth": {
      "score": 0,
      "history": []
    }
  }
}