{"assessment":{"deltas":[{"axis":"clarity","delta":1}],"note":"Names a specific condition — resetting scope now — that would make the next month sustainable, which is a mild positive clarity signal."},"new_queue":[{"ref_alias":"q_next_two_weeks_steadier","label":"Next two weeks steadier","name":"What would make the next two weeks feel steadier for you?","description":"Ends by converting the conversation into a concrete ask or adjustment without opening a new thread.","purpose":"wellbeing","stage":"lift","axis_effects":[{"axis":"wellbeing","delta":1},{"axis":"clarity","delta":1}]}]}