{"assessment":{"deltas":[{"axis":"wellbeing","delta":1},{"axis":"engagement","delta":1}],"note":"She says she is settling in, which is a mild positive on landing and investment; the unwritten-rules concern is a clarity signal worth probing next."},"new_queue":[{"ref_alias":null,"label":"Unwritten rules","name":"You mentioned 'unwritten rules' — what feels hardest to read in those meetings?","description":"Drills into the specific meeting norms or expectations that still feel opaque.","purpose":"topic","stage":"settling","axis_effects":[{"axis":"engagement","delta":1}]},{"ref_alias":"q_decision_boundaries","label":"Decision boundaries","name":"Where are the decision rights still fuzzy for you?","description":"Surfaces which choices she can make directly versus where she still needs to escalate.","purpose":"topic","stage":"orientation","axis_effects":[{"axis":"clarity","delta":3}]},{"ref_alias":"q_partner_expectations_3","label":"Partner expectations","name":"What expectations from partners are still hardest to read?","description":"Identifies which cross-functional relationships are creating uncertainty about what good looks like.","purpose":"topic","stage":"orientation","axis_effects":[{"axis":"clarity","delta":3},{"axis":"engagement","delta":1}]},{"ref_alias":"q_alignment_move_3","label":"Alignment move","name":"How are you handling alignment when priorities collide?","description":"Explores the concrete approach she uses to pre-wire decisions and move conflicting stakeholders forward.","purpose":"competency","stage":"blockers","axis_effects":[{"axis":"clarity","delta":1},{"axis":"growth","delta":1}]},{"ref_alias":"q_consensus_tradeoff","label":"Consensus tradeoff","name":"What do you tend to give up when you try to get everyone aligned?","description":"Surfaces whether she is over-indexing on consensus and what it costs in speed or decisiveness.","purpose":"competency","stage":"blockers","axis_effects":[{"axis":"clarity","delta":1},{"axis":"growth","delta":1}]},{"ref_alias":"q_meeting_signal","label":"Meeting signal","name":"What do you want your cross-functional updates to signal more clearly?","description":"Tests how she frames plans, tradeoffs, and ownership in meetings so partners read her intent correctly.","purpose":"competency","stage":"blockers","axis_effects":[{"axis":"clarity","delta":1},{"axis":"engagement","delta":1}]},{"ref_alias":"q_norms_support","label":"Norms support","name":"What would help you decode our norms faster?","description":"Opens the door for practical manager support around examples, decision paths, and feedback loops.","purpose":"topic","stage":"connection","axis_effects":[{"axis":"clarity","delta":3}]},{"ref_alias":"q_next_step_focus_8","label":"Next-step focus","name":"Given what we covered, where do you want to focus first?","description":"Closes by turning the discussion into a concrete priority for the next stretch.","purpose":"topic","stage":"connection","axis_effects":[{"axis":"clarity","delta":1},{"axis":"growth","delta":1}]},{"ref_alias":"q_support_style","label":"Support style","name":"What kind of feedback loop would be most useful from me right now?","description":"Finds the cadence and format of manager support that would reduce guesswork without adding noise.","purpose":"topic","stage":"connection","axis_effects":[{"axis":"clarity","delta":1},{"axis":"growth","delta":1}]}]}