{
  "raw": "{\"questions\":[{\"label\":\"Travel energy impact\",\"name\":\"How is frequent travel affecting your energy levels and motivation?\",\"description\":\"Explores how travel impacts Brian's energy and motivation.\",\"purpose\":\"wellbeing\",\"stage\":\"pulse\",\"axis_effects\":[{\"axis\":\"wellbeing\",\"delta\":3}]},{\"label\":\"Priority alignment\",\"name\":\"Which of your current priorities feels most critical right now?\",\"description\":\"Identifies which priorities Brian sees as most important.\",\"purpose\":\"topic\",\"stage\":\"friction\",\"axis_effects\":[{\"axis\":\"clarity\",\"delta\":3}]},{\"label\":\"Managing travel workload\",\"name\":\"What strategies are you using to manage your workload with all the travel?\",\"description\":\"Probes how Brian manages his workload given travel demands.\",\"purpose\":\"topic\",\"stage\":\"friction\",\"axis_effects\":[{\"axis\":\"wellbeing\",\"delta\":1},{\"axis\":\"clarity\",\"delta\":1}]},{\"label\":\"Support needs\",\"name\":\"What kind of support from me would make your workload more manageable?\",\"description\":\"Surfaces what support Brian needs from the manager.\",\"purpose\":\"topic\",\"stage\":\"friction\",\"axis_effects\":[{\"axis\":\"engagement\",\"delta\":3}]},{\"label\":\"Next steps clarity\",\"name\":\"What do you need to move forward confidently in the next two weeks?\",\"description\":\"Clarifies what Brian needs to maintain momentum.\",\"purpose\":\"competency\",\"stage\":\"momentum\",\"axis_effects\":[{\"axis\":\"clarity\",\"delta\":3}]},{\"label\":\"Delegation and focus\",\"name\":\"What tasks could you delegate to maintain focus on your priorities?\",\"description\":\"Encourages Brian to consider delegation to focus on priorities.\",\"purpose\":\"competency\",\"stage\":\"momentum\",\"axis_effects\":[{\"axis\":\"growth\",\"delta\":1}]},{\"label\":\"Travel recovery\",\"name\":\"How are you managing recovery after trips?\",\"description\":\"Explores how Brian recovers from the fatigue of traveling.\",\"purpose\":\"wellbeing\",\"stage\":\"momentum\",\"axis_effects\":[{\"axis\":\"wellbeing\",\"delta\":3}]},{\"label\":\"Priority setting\",\"name\":\"What would make the next two weeks feel more balanced?\",\"description\":\"Encourages Brian to identify areas for improvement in balance.\",\"purpose\":\"wellbeing\",\"stage\":\"lift\",\"axis_effects\":[{\"axis\":\"wellbeing\",\"delta\":1}]}]}",
  "saved_aliases": [
    "q_travel_energy_impact",
    "q_priority_alignment_11",
    "q_managing_travel_workload",
    "q_support_needs_12",
    "q_next_steps_clarity_3",
    "q_delegation_and_focus",
    "q_travel_recovery",
    "q_priority_setting"
  ]
}