{"assessment":{"deltas":[{"axis":"clarity","delta":-3}],"note":"He names a specific gap in cross-org alignment, indicating a strong clarity deficit around how to operate in political stakeholder situations. [THREAD-DEFERRED] Concrete thread: 'cross-org alignment' hesitation not drilled because drill cap requires advancing the arc."},"new_queue":[{"ref_alias":"q_intro_growth_stretch","label":"Stretch now","name":"Which part of your current work is actually stretching you right now?","description":"Distinguishes comfort-zone execution from genuine growth moments.","purpose":"topic","stage":"anchor","axis_effects":[{"axis":"growth","delta":3},{"axis":"engagement","delta":1}]},{"ref_alias":"q_current_scope_2","label":"Current scope","name":"What's feeling most solid in your role right now, Ahmed?","description":"Surfaces the parts of his current scope that are stable before moving into stretch or change.","purpose":"wellbeing","stage":"anchor","axis_effects":[{"axis":"engagement","delta":1},{"axis":"clarity","delta":1}]},{"ref_alias":"q_intro_growth_direction","label":"Direction","name":"When you imagine yourself eighteen months from now, what's actually different?","description":"Probes whether they have a real picture of where they want to go.","purpose":"topic","stage":"aspiration","axis_effects":[{"axis":"growth","delta":3},{"axis":"engagement","delta":1}]},{"ref_alias":"q_next_level_scope","label":"Next-level scope","name":"What does senior scope mean to you in practice?","description":"Asks him to define the next-level role in concrete terms rather than abstract ambition.","purpose":"topic","stage":"aspiration","axis_effects":[{"axis":"growth","delta":3},{"axis":"clarity","delta":1}]},{"ref_alias":"q_trade_offs_ahead","label":"Trade-offs ahead","name":"What are you choosing not to own over the next six to twelve weeks?","description":"Forces a real prioritisation conversation around strategic ownership and trade-offs.","purpose":"topic","stage":"investment","axis_effects":[{"axis":"clarity","delta":3},{"axis":"growth","delta":1}]},{"ref_alias":"q_first_move_6","label":"First move","name":"Given what we've covered, where do you want to focus first?","description":"Closes by turning the conversation into one concrete next move.","purpose":"topic","stage":"commitment","axis_effects":[{"axis":"growth","delta":1},{"axis":"clarity","delta":1}]}]}