{"assessment":{"deltas":[{"axis":"clarity","delta":-3}],"note":"He describes delaying help-seeking because he is trying to solve things alone first, which strongly signals unclear shipping expectations and escalation norms."},"new_queue":[{"ref_alias":null,"label":"Ask earlier","name":"When you hold off asking, what tells you it is time to pull someone in?","description":"Drills into his help-seeking threshold so the manager can make escalation expectations explicit.","purpose":"competency","stage":"orientation","axis_effects":[{"axis":"clarity","delta":3}]},{"ref_alias":"q_confidence_trigger","label":"Confidence trigger","name":"What tends to make you pause before shipping a ticket?","description":"Surfaces the concrete trigger behind late reassurance-seeking.","purpose":"competency","stage":"blockers","axis_effects":[{"axis":"clarity","delta":1},{"axis":"growth","delta":1}]},{"ref_alias":"q_waiting_on_piece","label":"Waiting on piece","name":"What are you usually waiting on when work starts to feel stuck?","description":"Identifies the missing decision, artifact, or input that slows him down.","purpose":"topic","stage":"blockers","axis_effects":[{"axis":"clarity","delta":3}]},{"ref_alias":"q_support_cadence","label":"Support cadence","name":"What kind of check-in from me would be most useful over the next two weeks?","description":"Helps line up a lightweight support rhythm without over-managing.","purpose":"topic","stage":"connection","axis_effects":[{"axis":"clarity","delta":1},{"axis":"wellbeing","delta":1}]},{"ref_alias":"q_two_week_takeaway","label":"Two-week takeaway","name":"What’s the one thing you want to have changed by our next check-in?","description":"Closes on a concrete commitment for the next two weeks.","purpose":"topic","stage":"connection","axis_effects":[{"axis":"growth","delta":1},{"axis":"clarity","delta":1}]}]}