{
  "turn": 9,
  "question": {
    "alias": "q_next_two_weeks_12",
    "label": "Next two weeks",
    "name": "Given what we’ve talked through, what’s the first concrete thing you want to change before we meet again?",
    "description": "Closes on a specific commitment without introducing a new thread.",
    "purpose": "topic",
    "stage": "lift",
    "axis_effects": {
      "growth": 1,
      "clarity": 1
    },
    "source": "generated"
  },
  "answer": "(skipped)",
  "skipped": true,
  "assessment": {
    "deltas": {},
    "note": "[SKIP] no signal — planner bypassed, queue carried forward"
  },
  "new_queue": [
    {
      "alias": "q_next_focus",
      "label": "Next focus",
      "name": "Given what we've covered, where do you want to focus first?"
    }
  ],
  "issues": [],
  "axis_state": {
    "wellbeing": {
      "score": -8,
      "history": [
        {
          "q": "q_intro_biweekly_pace",
          "delta": -3,
          "answer_excerpt": "I am proud of the outcomes, but the pace should not be normal."
        },
        {
          "q": "q_intro_biweekly_priorities",
          "delta": -1,
          "answer_excerpt": "I still do not get enough substantive feedback on key decisions."
        },
        {
          "q": "q_load_relief",
          "delta": -3,
          "answer_excerpt": "If we reset scope now, the next month is sustainable."
        }
      ]
    },
    "engagement": {
      "score": -6,
      "history": [
        {
          "q": "q_intro_biweekly_friction",
          "delta": -1,
          "answer_excerpt": "The last stretch shipped, but it was heavier than I made it sound."
        },
        {
          "q": "q_heavier_than_sounded_2",
          "delta": -3,
          "answer_excerpt": "Late nights came from carrying decision bottlenecks and final reviews."
        },
        {
          "q": "q_decision_bottlenecks_3",
          "delta": -1,
          "answer_excerpt": "Some of that work could have moved to the team sooner."
        },
        {
          "q": "q_intro_biweekly_pace",
          "delta": 1,
          "answer_excerpt": "I am proud of the outcomes, but the pace should not be normal."
        },
        {
          "q": "q_intro_biweekly_priorities",
          "delta": -1,
          "answer_excerpt": "I still do not get enough substantive feedback on key decisions."
        }
      ]
    },
    "clarity": {
      "score": -7,
      "history": [
        {
          "q": "q_intro_biweekly_friction",
          "delta": -1,
          "answer_excerpt": "The last stretch shipped, but it was heavier than I made it sound."
        },
        {
          "q": "q_intro_biweekly_priorities",
          "delta": -3,
          "answer_excerpt": "I still do not get enough substantive feedback on key decisions."
        },
        {
          "q": "q_decision_feedback_2",
          "delta": -3,
          "answer_excerpt": "I want clearer ownership boundaries so I am not default escalation."
        },
        {
          "q": "q_ownership_boundaries_2",
          "delta": 1,
          "answer_excerpt": "Next I want to hand off one stream end-to-end and stay out of the middle."
        },
        {
          "q": "q_load_relief",
          "delta": -1,
          "answer_excerpt": "If we reset scope now, the next month is sustainable."
        }
      ]
    },
    "growth": {
      "score": 0,
      "history": [
        {
          "q": "q_decision_feedback_2",
          "delta": -3,
          "answer_excerpt": "I want clearer ownership boundaries so I am not default escalation."
        },
        {
          "q": "q_ownership_boundaries_2",
          "delta": 3,
          "answer_excerpt": "Next I want to hand off one stream end-to-end and stay out of the middle."
        }
      ]
    }
  }
}