{"assessment":{"deltas":[{"axis":"clarity","delta":-1},{"axis":"wellbeing","delta":-1}],"note":"Deficiency-as-request: he names missing ownership and clearer guardrails as what would make things steadier, signalling mild clarity and wellbeing strain. [THREAD-DEFERRED-WINDDOWN] 'more ownership' and 'clearer guardrails' should be picked up next session."},"new_queue":[{"ref_alias":"q_steadier_next_two_weeks","label":"Steadier next two weeks","name":"What support from me would make the biggest difference on that?","description":"Closes by inviting the most useful manager support without opening a new thread.","purpose":"wellbeing","stage":"support","axis_effects":[{"axis":"clarity","delta":1},{"axis":"wellbeing","delta":1}]}]}